{
  "project_info": {
    "project_number": "1066246299744",
    "project_id": "finance-baa9c",
    "storage_bucket": "finance-baa9c.firebasestorage.app"
  },
  "client": [
    {
      "client_info": {
        "mobilesdk_app_id": "1:1066246299744:android:176ee08ba0de6025452305",
        "android_client_info": {
          "package_name": "com.example.myfinance"
        }
      },
      "oauth_client": [],
      "api_key": [
        {
          "current_key": "AIzaSyC5vlDmO6JaKaWetxCSHJgcympVC_oUSE8"
        }
      ],
      "services": {
        "appinvite_service": {
          "other_platform_oauth_client": []
        }
      }
    }
  ],
  "configuration_version": "1"
}